setup.cfg
setup.py
anybase32/__init__.py
anybase32.egg-info/PKG-INFO
anybase32.egg-info/SOURCES.txt
anybase32.egg-info/dependency_links.txt
anybase32.egg-info/top_level.txt