Metadata-Version: 1.1
Name: anybase32
Version: 1.0.0
Summary: Encode and decode base32 strings using arbitrary alphabets
Home-page: https://github.com/alanblevins/anybase32
Author: Alan Blevins
Author-email: alan.blevins@gmail.com
License: MIT
Download-URL: https://github.com/alanblevins/anybase32/tarball/1.0.0
Keywords: base32,encode,decode
Platform: UNKNOWN
